rayspect/__init__.py
rayspect-0.0.1.dist-info/licenses/LICENSE
rayspect-0.0.1.dist-info/METADATA
rayspect-0.0.1.dist-info/WHEEL
rayspect-0.0.1.dist-info/top_level.txt
rayspect-0.0.1.dist-info/RECORD
