Metadata-Version: 2.4
Name: rayspect
Version: 0.0.1
Summary: RaySpect: open-source tools for ray tracing and optical analysis.
Author-email: John Capone <jicapone.optics@gmail.com>
License: MIT
Classifier: Development Status :: 1 - Planning
Classifier: Intended Audience :: Science/Research
Classifier: License :: OSI Approved :: MIT License
Classifier: Programming Language :: Python :: 3
Requires-Python: >=3.8
License-File: LICENSE
Requires-Dist: numpy
Requires-Dist: matplotlib
Requires-Dist: scipy
Requires-Dist: cupy
Dynamic: license-file
